basepak/__init__.py
basepak/archive.py
basepak/complete.py
basepak/configer.py
basepak/confirm.py
basepak/consts.py
basepak/credentials.py
basepak/dotenv
basepak/exceptions.py
basepak/execute.py
basepak/igz_mgmt_handler.py
basepak/k8s_utils.py
basepak/locks.py
basepak/log.py
basepak/platform_api.py
basepak/stats.py
basepak/strings.py
basepak/tail.py
basepak/tasks.py
basepak/time.py
basepak/units.py
basepak/versioning.py
basepak/templates/__init__.py
basepak/templates/batch_job.py
basepak/templates/daemonset.py
basepak/templates/persistent_volume_claim.py
basepak-0.0.113.dist-info/METADATA
basepak-0.0.113.dist-info/WHEEL
basepak-0.0.113.dist-info/licenses/LICENSE.txt
basepak-0.0.113.dist-info/RECORD
