Metadata-Version: 2.4
Name: basepak
Version: 0.0.113
Summary: Iguazio CLI SDK
Project-URL: Documentation, https://github.com/tomaDev/basepak#readme
Project-URL: Issues, https://github.com/tomaDev/basepak/issues
Project-URL: Source, https://github.com/tomaDev/basepak
Author-email: tomaDev <genins21@gmail.com>
License-File: LICENSE.txt
Classifier: Development Status :: 4 - Beta
Classifier: Programming Language :: Python
Classifier: Programming Language :: Python :: 3.9
Classifier: Programming Language :: Python :: 3.10
Classifier: Programming Language :: Python :: 3.11
Classifier: Programming Language :: Python :: 3.12
Classifier: Programming Language :: Python :: 3.13
Classifier: Programming Language :: Python :: Implementation :: CPython
Classifier: Programming Language :: Python :: Implementation :: PyPy
Requires-Python: >=3.9
Requires-Dist: click
Requires-Dist: igz-mgmt
Requires-Dist: python-dotenv
Requires-Dist: requests
Requires-Dist: rich
Requires-Dist: ruyaml
Requires-Dist: tenacity
